AUTHORS
LICENSE
MANIFEST.in
README.rst
setup.py
captcha/__init__.py
captcha/fields.py
captcha/forms.py
captcha/views.py
captcha/widgets.py
django_recaptcha_mozilla.egg-info/PKG-INFO
django_recaptcha_mozilla.egg-info/SOURCES.txt
django_recaptcha_mozilla.egg-info/dependency_links.txt
django_recaptcha_mozilla.egg-info/requires.txt
django_recaptcha_mozilla.egg-info/top_level.txt