Metadata-Version: 1.0
Name: django-recaptcha-mozilla
Version: 0.0.1
Summary: Mozilla fork of django recaptcha form field/widget app.
Home-page: http://github.com/mozilla/django-recaptcha
Author: Praekelt Foundation
Author-email: dev@praekelt.com
License: BSD
Platform: UNKNOWN
Classifier: Programming Language :: Python
Classifier: License :: OSI Approved :: BSD License
Classifier: Development Status :: 4 - Beta
Classifier: Operating System :: OS Independent
Classifier: Framework :: Django
Classifier: Intended Audience :: Developers
Classifier: Topic :: Internet :: WWW/HTTP :: Dynamic Content
